fcsigner/__init__.py
fcsigner/__main__.py
fcsigner/fcsigner.py
file_checksum_signer-1.1.1.dist-info/METADATA
file_checksum_signer-1.1.1.dist-info/WHEEL
file_checksum_signer-1.1.1.dist-info/licenses/LICENSE
file_checksum_signer-1.1.1.dist-info/RECORD
